restful_api_guidelines_linter/__init__.py
restful_api_guidelines_linter/__main__.py
restful_api_guidelines_linter/cli.py
restful_api_guidelines_linter-0.2.dist-info/DESCRIPTION.rst
restful_api_guidelines_linter-0.2.dist-info/METADATA
restful_api_guidelines_linter-0.2.dist-info/RECORD
restful_api_guidelines_linter-0.2.dist-info/WHEEL
restful_api_guidelines_linter-0.2.dist-info/entry_points.txt
restful_api_guidelines_linter-0.2.dist-info/metadata.json
restful_api_guidelines_linter-0.2.dist-info/top_level.txt
