Metadata-Version: 2.0
Name: restful-api-guidelines-linter
Version: 0.2
Summary: UNKNOWN
Home-page: https://github.com/zalando-incubator/restful-api-guidelines-linter
Author: Zalando SE
Author-email: UNKNOWN
License: UNKNOWN
Platform: UNKNOWN
Classifier: Programming Language :: Python
Classifier: Programming Language :: Python :: 3.4
Classifier: Programming Language :: Python :: 3.5
Classifier: Development Status :: 5 - Production/Stable
Classifier: Intended Audience :: Developers
Classifier: Operating System :: OS Independent
Requires-Dist: PyYAML (>=3.12)
Requires-Dist: clickclick (>=1.2)
Requires-Dist: inflect
Requires-Dist: jsonschema (>=2.5.1)
Requires-Dist: strict-rfc3339 (>=0.6)
Requires-Dist: swagger-spec-validator (>=2.0.2)
